tapsilat_py/__init__.py
tapsilat_py/client.py
tapsilat_py/exceptions.py
tapsilat_py/models.py
tapsilat_py/validators.py
tapsilat_py-2025.12.8.1.dist-info/licenses/LICENSE
tapsilat_py-2025.12.8.1.dist-info/METADATA
tapsilat_py-2025.12.8.1.dist-info/WHEEL
tapsilat_py-2025.12.8.1.dist-info/top_level.txt
tapsilat_py-2025.12.8.1.dist-info/RECORD
