Metadata-Version: 2.4
Name: tapsilat-py
Version: 2025.12.8.1
Summary: Client SDK for Tapsilat API
Home-page: https://github.com/tapsilat/tapsilat-py
Author: Tapsilat
Author-email: support@tapsilat.dev
Project-URL: Source Code, https://github.com/tapsilat/tapsilat-py
Classifier: Programming Language :: Python :: 3
Classifier: License :: OSI Approved :: Apache Software License
Classifier: Operating System :: OS Independent
Requires-Python: >=3.6
License-File: LICENSE
Requires-Dist: requests>=2.25.0
Dynamic: author
Dynamic: author-email
Dynamic: classifier
Dynamic: description
Dynamic: description-content-type
Dynamic: home-page
Dynamic: license-file
Dynamic: project-url
Dynamic: requires-dist
Dynamic: requires-python
Dynamic: summary
